MANIFEST.in
README.rst
setup.py
SuperParamiko/__init__.py
SuperParamiko.egg-info/PKG-INFO
SuperParamiko.egg-info/SOURCES.txt
SuperParamiko.egg-info/dependency_links.txt
SuperParamiko.egg-info/not-zip-safe
SuperParamiko.egg-info/requires.txt
SuperParamiko.egg-info/top_level.txt