Metadata-Version: 1.1
Name: SuperParamiko
Version: 0.1.1
Summary: Wrapper around paramiko adding pbs style functionality
Home-page: http://github.com/rossdylan/SuperParamiko
Author: Ross Delinger
Author-email: rossdylan@csh.rit.edu
License: AGPLv3+
Keywords: ssh paramiko
Platform: UNKNOWN
Classifier: Programming Language :: Python
Classifier: License :: OSI Approved :: GNU Affero General Public License v3 or later (AGPLv3+)
